LICENSE
README.md
setup.py
src/inplus/__init__.py
src/inplus/_inplus.py
src/inplus.egg-info/PKG-INFO
src/inplus.egg-info/SOURCES.txt
src/inplus.egg-info/dependency_links.txt
src/inplus.egg-info/top_level.txt