Metadata-Version: 2.1
Name: inplus
Version: 1.0.0
Summary: efficient input methods.
Home-page: https://github.com/kedarrio/inplus
Author: kedarr
License: MIT
Keywords: inplus,input,input methods,input methods for python
Classifier: Programming Language :: Python :: 3
Classifier: Programming Language :: Python :: 3.9
Classifier: Programming Language :: Python :: 3.10
Classifier: Intended Audience :: Developers
Classifier: License :: OSI Approved :: MIT License
Classifier: Topic :: Utilities
Requires-Python: >=3.9
License-File: LICENSE
